escape/__init__.py
escape/storage/__init__.py
escape/storage/tests.py
escape/stream/__init__.py
escape/stream/es_wrappers.py
escape/stream/escape_stream.py
escape/stream/plots.py
escape/stream/setup.py
escape/stream/testStream.py
escape/stream/tools.py
escape/stream/toolsPlot.py
escape_fel-0.0.1.dist-info/METADATA
escape_fel-0.0.1.dist-info/RECORD
escape_fel-0.0.1.dist-info/WHEEL
escape_fel-0.0.1.dist-info/top_level.txt
