Metadata-Version: 2.1
Name: escape-fel
Version: 0.0.1
Summary: UNKNOWN
Home-page: https://github.com/htlemke/escape
Author: HLemke
Author-email: htlemke@gmail.com
License: UNKNOWN
Platform: UNKNOWN
Classifier: Programming Language :: Python :: 3
Classifier: License :: OSI Approved :: MIT License
Classifier: Operating System :: OS Independent
Requires: dask
Requires: numpy
Requires: h5py
